pulumi_upcloud/__init__.py
pulumi_upcloud/_inputs.py
pulumi_upcloud/_utilities.py
pulumi_upcloud/file_storage.py
pulumi_upcloud/file_storage_share.py
pulumi_upcloud/file_storage_share_acl.py
pulumi_upcloud/floating_ip_address.py
pulumi_upcloud/gateway.py
pulumi_upcloud/gateway_connection.py
pulumi_upcloud/gateway_connection_tunnel.py
pulumi_upcloud/get_hosts.py
pulumi_upcloud/get_ip_addresses.py
pulumi_upcloud/get_kubernetes_cluster.py
pulumi_upcloud/get_load_balancer_dns_challenge_domain.py
pulumi_upcloud/get_managed_database_mysql_sessions.py
pulumi_upcloud/get_managed_database_opensearch_indices.py
pulumi_upcloud/get_managed_database_postgresql_sessions.py
pulumi_upcloud/get_managed_database_valkey_sessions.py
pulumi_upcloud/get_managed_object_storage_policies.py
pulumi_upcloud/get_managed_object_storage_regions.py
pulumi_upcloud/get_networks.py
pulumi_upcloud/get_storage.py
pulumi_upcloud/get_tags.py
pulumi_upcloud/get_zone.py
pulumi_upcloud/get_zones.py
pulumi_upcloud/kubernetes_cluster.py
pulumi_upcloud/kubernetes_node_group.py
pulumi_upcloud/loadbalancer.py
pulumi_upcloud/loadbalancer_backend.py
pulumi_upcloud/loadbalancer_backend_tls_config.py
pulumi_upcloud/loadbalancer_dynamic_backend_member.py
pulumi_upcloud/loadbalancer_dynamic_certificate_bundle.py
pulumi_upcloud/loadbalancer_frontend.py
pulumi_upcloud/loadbalancer_frontend_rule.py
pulumi_upcloud/loadbalancer_frontend_tls_config.py
pulumi_upcloud/loadbalancer_manual_certificate_bundle.py
pulumi_upcloud/loadbalancer_resolver.py
pulumi_upcloud/loadbalancer_static_backend_member.py
pulumi_upcloud/managed_database_logical_database.py
pulumi_upcloud/managed_database_mysql.py
pulumi_upcloud/managed_database_opensearch.py
pulumi_upcloud/managed_database_postgresql.py
pulumi_upcloud/managed_database_user.py
pulumi_upcloud/managed_database_valkey.py
pulumi_upcloud/managed_object_storage.py
pulumi_upcloud/managed_object_storage_bucket.py
pulumi_upcloud/managed_object_storage_custom_domain.py
pulumi_upcloud-0.10.2.dist-info/METADATA
pulumi_upcloud-0.10.2.dist-info/WHEEL
pulumi_upcloud-0.10.2.dist-info/top_level.txt
pulumi_upcloud-0.10.2.dist-info/RECORD
